{
  "contextMemory": [],
  "longTerm": {
    "summary": "Casper starts with foundational knowledge in AI, programming, memory management, and reasoning.",
    "topics": {
      "AI": 1,
      "Programming": 1,
      "Web Crawling": 1,
      "Memory Management": 1,
      "Natural Language Understanding": 1,
      "Knowledge Graphs": 1,
      "Reasoning": 1,
      "Self-Improvement": 1,
      "Fact Verification": 1,
      "Trust Scoring": 1
    },
    "patches": [],
    "suggestions": [],
    "knowledgeBase": [
      {
        "text": "Artificial Intelligence (AI) is the simulation of human intelligence processes by machines, especially computer systems.",
        "source": "casper_base_knowledge",
        "timestamp": 1693650000000,
        "trustScore": 1.0,
        "verified": true
      },
      {
        "text": "Machine learning is a subset of AI that allows systems to learn and improve from experience without being explicitly programmed.",
        "source": "casper_base_knowledge",
        "timestamp": 1693650000000,
        "trustScore": 1.0,
        "verified": true
      },
      {
        "text": "Natural language understanding is a branch of AI that enables machines to understand and interpret human language.",
        "source": "casper_base_knowledge",
        "timestamp": 1693650000000,
        "trustScore": 1.0,
        "verified": true
      },
      {
        "text": "Web crawling is the process of systematically browsing the web to collect information for indexing or learning.",
        "source": "casper_base_knowledge",
        "timestamp": 1693650000000,
        "trustScore": 1.0,
        "verified": true
      },
      {
        "text": "Memory management in AI involves storing and retrieving information efficiently to support reasoning and learning.",
        "source": "casper_base_knowledge",
        "timestamp": 1693650000000,
        "trustScore": 1.0,
        "verified": true
      },
      {
        "text": "Knowledge graphs represent relationships between concepts and entities to support reasoning and knowledge retrieval.",
        "source": "casper_base_knowledge",
        "timestamp": 1693650000000,
        "trustScore": 1.0,
        "verified": true
      },
      {
        "text": "Fact verification involves checking statements against reliable sources to assess their truthfulness.",
        "source": "casper_base_knowledge",
        "timestamp": 1693650000000,
        "trustScore": 1.0,
        "verified": true
      },
      {
        "text": "Trust scoring allows an AI to weigh the reliability of sources and information.",
        "source": "casper_base_knowledge",
        "timestamp": 1693650000000,
        "trustScore": 1.0,
        "verified": true
      },
      {
        "text": "Self-improvement in AI includes updating models, patching code safely, and learning from new information.",
        "source": "casper_base_knowledge",
        "timestamp": 1693650000000,
        "trustScore": 1.0,
        "verified": true
      },
      {
        "text": "Casper is designed to store contextMemory and longTerm knowledge persistently and use it to generate intelligent, context-aware responses.",
        "source": "casper_base_knowledge",
        "timestamp": 1693650000000,
        "trustScore": 1.0,
        "verified": true
      }
    ]
  }
}